{
    "info": {
		"_postman_id"   : "6448ac71-15a0-4a84-b3f7-3ea3704fe90e",
		"name"          : "@apps - common/administrative-area-level-2",
		"schema"        : "https://schema.getpostman.com/json/collection/v2.1.0/collection.json"
    },
    "item": [
        {
			"name": "GraphQL - commonCreateAdministrativeAreaLevel2",
			"request": {
				"method": "POST",
				"header": [
                ],
				"body": {
					"mode": "graphql",
					"graphql": {
						"query": "mutation ($payload:CommonCreateAdministrativeAreaLevel2Input!)\n{\n\tcommonCreateAdministrativeAreaLevel2 (payload:$payload)\n\t{\n\t\tid\n\t\tcountryId\n\t\tadministrativeAreaLevel1Id\n\t\tcode\n\t\tcustomCode\n\t\tname\n\t\tslug\n\t\tlatitude\n\t\tlongitude\n\t\tzoom\n\t}\n}",
                        "variables": "{\n\t\"payload\":\n\t{\n\t\t\"id\": \"5b19d6ac-4081-573b-96b3-56964d5326a8\", \n\t\t\"countryId\": \"5b19d6ac-4081-573b-96b3-56964d5326a8\", \n\t\t\"administrativeAreaLevel1Id\": \"5b19d6ac-4081-573b-96b3-56964d5326a8\", \n\t\t\"code\": \"0ey12hcl\", \n\t\t\"customCode\": \"cqft736jki\", \n\t\t\"name\": \"Practical Soft Ball\", \n\t\t\"slug\": \"repellat-qui-voluptatem\", \n\t\t\"latitude\": 44563533162878180, \n\t\t\"longitude\": 93897326810718530, \n\t\t\"zoom\": 79\n\t}\n}"
					}
				},
				"url": {
					"raw": "{{URL}}/graphql",
					"host": [
						"{{URL}}"
					],
					"path": [
						"graphql"
					]
				}
			},
			"response": []
        },
        {
			"name": "GraphQL - commonCreateAdministrativeAreasLevel2",
			"request": {
				"method": "POST",
				"header": [],
				"body": {
					"mode": "graphql",
					"graphql": {
						"query": "mutation ($payload:[CommonCreateAdministrativeAreaLevel2Input]!)\n{\n\tcommonCreateAdministrativeAreasLevel2 (payload:$payload)\n}",
						"variables": "{\n\t\"payload\":\n\t[\n\t\t{\n\t\t\t\"id\": \"8ba79afe-4a89-416b-8d12-228b2b1a5a61\", \n\t\t\t\"countryId\": \"d5efc549-cab1-4662-86a5-49d7de371a1c\", \n\t\t\t\"administrativeAreaLevel1Id\": \"7743d4a7-39bc-4414-ac43-6129bb0d26f9\", \n\t\t\t\"code\": \"cruaoz01\", \n\t\t\t\"customCode\": \"vgtvv1nlhr\", \n\t\t\t\"name\": \"Ergonomic Wooden Ball\", \n\t\t\t\"slug\": \"optio-animi-pariatur\", \n\t\t\t\"latitude\": 79814016011011150, \n\t\t\t\"longitude\": 39509001828552024, \n\t\t\t\"zoom\": 26\n\t\t}, \n\t\t{\n\t\t\t\"id\": \"fd4e9668-e597-42f3-949c-b60fde89ea73\", \n\t\t\t\"countryId\": \"8341449d-ee2e-4cbc-9564-03be706a56fd\", \n\t\t\t\"administrativeAreaLevel1Id\": \"432946c3-7e84-4b6d-9b31-6551b398c061\", \n\t\t\t\"code\": \"avlq3vnu\", \n\t\t\t\"customCode\": \"r5jswtwlqb\", \n\t\t\t\"name\": \"Unbranded Granite Hat\", \n\t\t\t\"slug\": \"culpa-sit-optio\", \n\t\t\t\"latitude\": 63372890087890504, \n\t\t\t\"longitude\": 71103876530850120, \n\t\t\t\"zoom\": 80\n\t\t}, \n\t\t{\n\t\t\t\"id\": \"aafdbf15-86b2-4b24-9afe-3bf52fbd222e\", \n\t\t\t\"countryId\": \"a9f89a76-26fd-4329-b333-bac23c14e1fe\", \n\t\t\t\"administrativeAreaLevel1Id\": \"d9ac994b-3ca7-4e98-afb6-79b08066c726\", \n\t\t\t\"code\": \"m3vr47wg\", \n\t\t\t\"customCode\": \"qh64dybecu\", \n\t\t\t\"name\": \"Handcrafted Fresh Hat\", \n\t\t\t\"slug\": \"magnam-nihil-iure\", \n\t\t\t\"latitude\": 97314557009274530, \n\t\t\t\"longitude\": 12067352600128068, \n\t\t\t\"zoom\": 93\n\t\t}, \n\t\t{\n\t\t\t\"id\": \"f0ef14b6-e9a0-4b32-bcc1-3dbf858584cf\", \n\t\t\t\"countryId\": \"682b054f-f7ab-4407-995f-2a428533222a\", \n\t\t\t\"administrativeAreaLevel1Id\": \"bd2c8d7d-8d3b-41cf-9e00-a44eeb08441b\", \n\t\t\t\"code\": \"m1a3gbq0\", \n\t\t\t\"customCode\": \"1mt100de1p\", \n\t\t\t\"name\": \"Intelligent Cotton Keyboard\", \n\t\t\t\"slug\": \"aspernatur-voluptate-quia\", \n\t\t\t\"latitude\": 16532745152281464, \n\t\t\t\"longitude\": 26852542578635550, \n\t\t\t\"zoom\": 51\n\t\t}, \n\t\t{\n\t\t\t\"id\": \"7bbc154a-c38d-4d1f-8bec-add1e220ad75\", \n\t\t\t\"countryId\": \"c9a8d017-b109-43f9-a156-ece2c6e12c39\", \n\t\t\t\"administrativeAreaLevel1Id\": \"4c5370d8-c7ba-4591-916b-b1f8ca27dc3d\", \n\t\t\t\"code\": \"a79k0wm6\", \n\t\t\t\"customCode\": \"s5soc4ukh4\", \n\t\t\t\"name\": \"Tasty Plastic Keyboard\", \n\t\t\t\"slug\": \"quasi-ut-voluptate\", \n\t\t\t\"latitude\": 70901615195976990, \n\t\t\t\"longitude\": 89943145535347440, \n\t\t\t\"zoom\": 71\n\t\t}, \n\t\t{\n\t\t\t\"id\": \"25122f10-ffad-4f65-be4b-35c650166698\", \n\t\t\t\"countryId\": \"a6aaa955-5736-46e0-afa1-f53056e37426\", \n\t\t\t\"administrativeAreaLevel1Id\": \"5110f9ea-cc57-4c6d-a1f3-6c38cf0a9e85\", \n\t\t\t\"code\": \"ptdg7h4s\", \n\t\t\t\"customCode\": \"nb1uv9wa7w\", \n\t\t\t\"name\": \"Generic Wooden Towels\", \n\t\t\t\"slug\": \"voluptas-non-vero\", \n\t\t\t\"latitude\": 97803439432250160, \n\t\t\t\"longitude\": 78371885161252580, \n\t\t\t\"zoom\": 21\n\t\t}, \n\t\t{\n\t\t\t\"id\": \"bdd7b30f-f77a-4288-8266-7510c468d5ba\", \n\t\t\t\"countryId\": \"c327d784-27fb-42a5-8cbf-b6178e62275b\", \n\t\t\t\"administrativeAreaLevel1Id\": \"4fde2b58-008b-4235-9d4e-b58ec93eb02b\", \n\t\t\t\"code\": \"mae09rhr\", \n\t\t\t\"customCode\": \"9oywoiw8tw\", \n\t\t\t\"name\": \"Rustic Fresh Tuna\", \n\t\t\t\"slug\": \"accusamus-alias-recusandae\", \n\t\t\t\"latitude\": 94405642389876540, \n\t\t\t\"longitude\": 31347486182552796, \n\t\t\t\"zoom\": 44\n\t\t}, \n\t\t{\n\t\t\t\"id\": \"b108040f-4ab3-491d-9657-fc5dae93d4ac\", \n\t\t\t\"countryId\": \"36a459b9-622a-479b-a1fc-2ec71cc8d60f\", \n\t\t\t\"administrativeAreaLevel1Id\": \"0f90effe-a433-4ab5-bc42-99b5184f41f6\", \n\t\t\t\"code\": \"tqnt2j0e\", \n\t\t\t\"customCode\": \"y8ekyena2o\", \n\t\t\t\"name\": \"Licensed Fresh Computer\", \n\t\t\t\"slug\": \"voluptate-qui-ullam\", \n\t\t\t\"latitude\": 90587009834244860, \n\t\t\t\"longitude\": 27919395371667770, \n\t\t\t\"zoom\": 11\n\t\t}, \n\t\t{\n\t\t\t\"id\": \"5a5cd96a-a4bc-4f5f-809d-f1ade1c7c7f6\", \n\t\t\t\"countryId\": \"fcad71dd-473e-4c7f-8ed1-794354bafc51\", \n\t\t\t\"administrativeAreaLevel1Id\": \"5e106756-70e9-42c4-9e60-69939f37ba6d\", \n\t\t\t\"code\": \"blce00vd\", \n\t\t\t\"customCode\": \"uhy5fjttqy\", \n\t\t\t\"name\": \"Rustic Frozen Fish\", \n\t\t\t\"slug\": \"veniam-fugit-sunt\", \n\t\t\t\"latitude\": 85301836912248420, \n\t\t\t\"longitude\": 72247702502379710, \n\t\t\t\"zoom\": 18\n\t\t}, \n\t\t{\n\t\t\t\"id\": \"2171e9db-894f-4732-addf-3c2176968f3a\", \n\t\t\t\"countryId\": \"58938010-bfcd-4f42-b3d6-d6a121a07386\", \n\t\t\t\"administrativeAreaLevel1Id\": \"7cedbb64-bbbd-47fc-adab-6d8ca3b656ae\", \n\t\t\t\"code\": \"uqit6vv3\", \n\t\t\t\"customCode\": \"cepcb559qm\", \n\t\t\t\"name\": \"Rustic Granite Car\", \n\t\t\t\"slug\": \"corporis-nostrum-ad\", \n\t\t\t\"latitude\": 29724112885574290, \n\t\t\t\"longitude\": 67093678203890910, \n\t\t\t\"zoom\": 29\n\t\t}\n\t]\n}"
					}
				},
				"url": {
					"raw": "{{URL}}/graphql",
					"host": [
						"{{URL}}"
					],
					"path": [
						"graphql"
					]
				}
			},
			"response": []
        },
        {
			"name": "GraphQL - commonPaginateAdministrativeAreasLevel2",
			"request": {
				"method": "POST",
				"header": [
                ],
				"body": {
					"mode": "graphql",
					"graphql": {
						"query": "query ($query:QueryStatement $constraint:QueryStatement)\n{\n\tcommonPaginateAdministrativeAreasLevel2 (query:$query constraint:$constraint)\n\t{\n\t\ttotal\n\t\tcount\n\t\trows\n\t}\n}",
						"variables": "{\n\t\"query\":\n\t{\n\t\t\"offset\": 0,\n\t\t\"limit\": 10\n\t}\n}"
					}
				},
				"url": {
					"raw": "{{URL}}/graphql",
					"host": [
						"{{URL}}"
					],
					"path": [
						"graphql"
					]
				}
			},
			"response": []
        },
        {
			"name": "GraphQL - commonGetAdministrativeAreasLevel2",
			"request": {
				"method": "POST",
				"header": [
                ],
				"body": {
					"mode": "graphql",
					"graphql": {
						"query": "query ($query:QueryStatement)\n{\n\tcommonGetAdministrativeAreasLevel2 (query: $query)\n\t{\n\t\tid\n\t\tcode\n\t\tcustomCode\n\t\tname\n\t\tslug\n\t\tlatitude\n\t\tlongitude\n\t\tzoom\n\t\tcreatedAt\n\t\tupdatedAt\n\t}\n}",
						"variables": "{\n\t\"query\":\n\t{\n\t\t\"where\":\n\t\t{ \n\t\t\t\"id\": \"5b19d6ac-4081-573b-96b3-56964d5326a8\"\n\t\t}\n\t}\n}"
					}
				},
				"url": {
					"raw": "{{URL}}/graphql",
					"host": [
						"{{URL}}"
					],
					"path": [
						"graphql"
					]
				}
			},
			"response": []
        },
        {
			"name": "GraphQL - commonFindAdministrativeAreaLevel2",
			"request": {
				"method": "POST",
				"header": [
                ],
				"body": {
					"mode": "graphql",
					"graphql": {
						"query": "query ($query:QueryStatement)\n{\n\tcommonFindAdministrativeAreaLevel2 (query: $query)\n\t{\n\t\tid\n\t\tcode\n\t\tcustomCode\n\t\tname\n\t\tslug\n\t\tlatitude\n\t\tlongitude\n\t\tzoom\n\t\tcreatedAt\n\t\tupdatedAt\n\t}\n}",
						"variables": "{\n\t\"query\":\n\t{\n\t\t\"where\":\n\t\t{\n\t\t\t\"id\": \"5b19d6ac-4081-573b-96b3-56964d5326a8\"\n\t\t}\n\t}\n}"
					}
				},
				"url": {
					"raw": "{{URL}}/graphql",
					"host": [
						"{{URL}}"
					],
					"path": [
						"graphql"
					]
				}
			},
			"response": []
        },
        {
			"name": "GraphQL - commonFindAdministrativeAreaLevel2ById",
			"request": {
				"method": "POST",
				"header": [
                ],
				"body": {
					"mode": "graphql",
					"graphql": {
						"query": "query ($id:ID)\n{\n\tcommonFindAdministrativeAreaLevel2ById (id:$id)\n\t{\n\t\tid\n\t\tcode\n\t\tcustomCode\n\t\tname\n\t\tslug\n\t\tlatitude\n\t\tlongitude\n\t\tzoom\n\t\tcreatedAt\n\t\tupdatedAt\n\t}\n}",
						"variables": "{\n\t\"id\": \"5b19d6ac-4081-573b-96b3-56964d5326a8\"\n}"
					}
				},
				"url": {
					"raw": "{{URL}}/graphql",
					"host": [
						"{{URL}}"
					],
					"path": [
						"graphql"
					]
				}
			},
			"response": []
        },
        {
			"name": "GraphQL - commonUpdateAdministrativeAreaLevel2",
			"request": {
				"method": "POST",
				"header": [
                ],
				"body": {
					"mode": "graphql",
					"graphql": {
						"query": "mutation ($payload:CommonUpdateAdministrativeAreaLevel2Input!)\n{\n\tcommonUpdateAdministrativeAreaLevel2 (payload:$payload)\n\t{\n\t\tid\n\t\tcode\n\t\tcustomCode\n\t\tname\n\t\tslug\n\t\tlatitude\n\t\tlongitude\n\t\tzoom\n\t\tcreatedAt\n\t\tupdatedAt\n\t}\n}",
						"variables": "{\n\t\"payload\":\n\t{\n\t\t\"id\": \"5b19d6ac-4081-573b-96b3-56964d5326a8\", \n\t\t\"countryId\": \"5b19d6ac-4081-573b-96b3-56964d5326a8\", \n\t\t\"administrativeAreaLevel1Id\": \"5b19d6ac-4081-573b-96b3-56964d5326a8\", \n\t\t\"code\": \"3ro6n6qt\", \n\t\t\"customCode\": \"xr6okjssqn\", \n\t\t\"name\": \"Ergonomic Plastic Tuna\", \n\t\t\"slug\": \"beatae-repellat-incidunt\", \n\t\t\"latitude\": 50302302988836240, \n\t\t\"longitude\": 97701987764375660, \n\t\t\"zoom\": 41\n\t}\n}"
					}
				},
				"url": {
					"raw": "{{URL}}/graphql",
					"host": [
						"{{URL}}"
					],
					"path": [
						"graphql"
					]
				}
			},
			"response": []
        },
        {
			"name": "GraphQL - commonDeleteAdministrativeAreaLevel2ById",
			"request": {
				"method": "POST",
				"header": [
                ],
				"body": {
					"mode": "graphql",
					"graphql": {
						"query": "mutation ($id:ID!)\n{\n\tcommonDeleteAdministrativeAreaLevel2ById (id:$id)\n\t{\n\t\tid\n\t\tcode\n\t\tcustomCode\n\t\tname\n\t\tslug\n\t\tlatitude\n\t\tlongitude\n\t\tzoom\n\t\tcreatedAt\n\t\tupdatedAt\n\t}\n}",
						"variables": "{\n\t\"id\": \"5b19d6ac-4081-573b-96b3-56964d5326a8\"\n}"
					}
				},
				"url": {
					"raw": "{{URL}}/graphql",
					"host": [
						"{{URL}}"
					],
					"path": [
						"graphql"
					]
				}
			},
			"response": []
        },
        {
			"name": "GraphQL - commonDeleteAdministrativeAreasLevel2",
			"request": {
				"method": "POST",
				"header": [
                ],
				"body": {
					"mode": "graphql",
					"graphql": {
						"query": "mutation ($query:QueryStatement)\n{\n\tcommonDeleteAdministrativeAreasLevel2 (query: $query)\n\t{\n\t\tid\n\t\tcode\n\t\tcustomCode\n\t\tname\n\t\tslug\n\t\tlatitude\n\t\tlongitude\n\t\tzoom\n\t\tcreatedAt\n\t\tupdatedAt\n\t}\n}",
						"variables": "{\n\t\"query\":\n\t{\n\t\t\"where\":\n\t\t{\n\t\t\t\"id\":\n\t\t\t{\n\t\t\t\t\"[substring]\": \"\"\n\t\t\t}\n\t\t}\n\t}\n}"
					}
				},
				"url": {
					"raw": "{{URL}}/graphql",
					"host": [
						"{{URL}}"
					],
					"path": [
						"graphql"
					]
				}
			},
			"response": []
        },
        {
			"name": "REST - common/administrative-area-level-2",
			"request": {
				"method": "POST",
				"header": [
					{
						"key"   : "Content-Type",
						"name"  : "Content-Type",
						"type"  : "text",
						"value" : "application/json"
					}				],
				"body": {
					"mode"  : "raw",
					"raw"   : "{\n\t\"id\": \"5b19d6ac-4081-573b-96b3-56964d5326a8\", \n\t\"countryId\": \"5b19d6ac-4081-573b-96b3-56964d5326a8\", \n\t\"administrativeAreaLevel1Id\": \"5b19d6ac-4081-573b-96b3-56964d5326a8\", \n\t\"code\": \"ceeh221a\", \n\t\"customCode\": \"p2eee831zm\", \n\t\"name\": \"Intelligent Fresh Car\", \n\t\"slug\": \"est-modi-porro\", \n\t\"latitude\": 69298985387792050, \n\t\"longitude\": 96383084305875100, \n\t\"zoom\": 12\n}",
					"options": {
						"raw": {
							"language": "json"
						}
					}
				},
				"url": {
					"raw": "{{URL}}/common/administrative-area-level-2",
					"host": [
						"{{URL}}"
					],
					"path": [
						"common",
						"administrative-area-level-2"
					]
				}
			},
			"response": []
        },
        {
			"name": "REST - common/administrative-areas-level-2",
			"request": {
				"method": "POST",
				"header": [
					{
						"key"   : "Content-Type",
						"name"  : "Content-Type",
						"type"  : "text",
						"value" : "application/json"
					}				],
				"body": {
					"mode"  : "raw",
					"raw"   : "[\n\t{\n\t\t\"id\": \"fb792b12-ddf3-4c0a-8208-d8f10e51863a\", \n\t\t\"countryId\": \"6335a521-b94b-4c6e-a62a-65bcb0fb4709\", \n\t\t\"administrativeAreaLevel1Id\": \"c1195c18-88de-4107-ba2f-1650b6e7d7e8\", \n\t\t\"code\": \"nc1uk7r6\", \n\t\t\"customCode\": \"zpnggbu8bo\", \n\t\t\"name\": \"Awesome Plastic Table\", \n\t\t\"slug\": \"quo-necessitatibus-molestiae\", \n\t\t\"latitude\": 94569213508195000, \n\t\t\"longitude\": 54456547282081770, \n\t\t\"zoom\": 70\n\t}, \n\t{\n\t\t\"id\": \"14df24b2-c7b5-4a72-bbe4-68203ff0c43b\", \n\t\t\"countryId\": \"dbc3654f-63a8-4067-9956-069530ac56d8\", \n\t\t\"administrativeAreaLevel1Id\": \"1b302d6f-cbf7-479a-9bc3-057412feced7\", \n\t\t\"code\": \"87l0zk62\", \n\t\t\"customCode\": \"b0zlmq1al4\", \n\t\t\"name\": \"Generic Metal Soap\", \n\t\t\"slug\": \"dolor-quo-vitae\", \n\t\t\"latitude\": 50715360242152580, \n\t\t\"longitude\": 39517533712397100, \n\t\t\"zoom\": 85\n\t}, \n\t{\n\t\t\"id\": \"d2e02928-cbc5-4910-a773-d98b91f39555\", \n\t\t\"countryId\": \"625ac459-1067-4eb6-847a-cf1ee1e07d9c\", \n\t\t\"administrativeAreaLevel1Id\": \"e975fca8-da61-44d6-abf5-2daa7cf71052\", \n\t\t\"code\": \"xcand7ka\", \n\t\t\"customCode\": \"8hb34zfaf5\", \n\t\t\"name\": \"Unbranded Frozen Gloves\", \n\t\t\"slug\": \"doloremque-aut-similique\", \n\t\t\"latitude\": 46976600047657220, \n\t\t\"longitude\": 48032337961184190, \n\t\t\"zoom\": 97\n\t}, \n\t{\n\t\t\"id\": \"601bf3bc-56bf-4c76-b5eb-906344d7cc0f\", \n\t\t\"countryId\": \"92095822-3b91-49b2-ac8a-26d52eda1a2a\", \n\t\t\"administrativeAreaLevel1Id\": \"ba44845a-868b-4370-a932-188f55983852\", \n\t\t\"code\": \"4a1h70a9\", \n\t\t\"customCode\": \"mekzso83vj\", \n\t\t\"name\": \"Unbranded Soft Mouse\", \n\t\t\"slug\": \"asperiores-quaerat-asperiores\", \n\t\t\"latitude\": 20681484800113664, \n\t\t\"longitude\": 69534861798498310, \n\t\t\"zoom\": 65\n\t}, \n\t{\n\t\t\"id\": \"22d4234d-1c55-45c5-9bfb-849dbfeb5a8d\", \n\t\t\"countryId\": \"8508c223-6452-498c-a887-9296a3e2c0d5\", \n\t\t\"administrativeAreaLevel1Id\": \"93250dbc-d7bb-4b61-b9c9-9cd26f1a66b5\", \n\t\t\"code\": \"hlrtwsee\", \n\t\t\"customCode\": \"1ra6htd4vv\", \n\t\t\"name\": \"Intelligent Soft Sausages\", \n\t\t\"slug\": \"ut-dolor-voluptatem\", \n\t\t\"latitude\": 99842573480841630, \n\t\t\"longitude\": 54072407502873420, \n\t\t\"zoom\": 29\n\t}, \n\t{\n\t\t\"id\": \"fe041238-f3d4-413e-b501-90fecfc299a5\", \n\t\t\"countryId\": \"28de8900-5de0-4679-b394-b97c27242132\", \n\t\t\"administrativeAreaLevel1Id\": \"d93c87eb-beda-42cd-b834-d6805fd0ccae\", \n\t\t\"code\": \"k9v7dbxg\", \n\t\t\"customCode\": \"fo35ejbt1k\", \n\t\t\"name\": \"Handmade Rubber Hat\", \n\t\t\"slug\": \"accusamus-consequatur-animi\", \n\t\t\"latitude\": 59360733046793830, \n\t\t\"longitude\": 20162499979152770, \n\t\t\"zoom\": 99\n\t}, \n\t{\n\t\t\"id\": \"91c17b66-7d1c-4ddc-81e0-76cbaa39fe01\", \n\t\t\"countryId\": \"7c4a656f-0a24-42e3-a2d3-834a747b35aa\", \n\t\t\"administrativeAreaLevel1Id\": \"44a9f2d7-fb92-47d9-a8c3-7d971549463f\", \n\t\t\"code\": \"j162yzmt\", \n\t\t\"customCode\": \"wablik408y\", \n\t\t\"name\": \"Unbranded Frozen Mouse\", \n\t\t\"slug\": \"asperiores-quidem-odio\", \n\t\t\"latitude\": 15153627792193776, \n\t\t\"longitude\": 90274321751303330, \n\t\t\"zoom\": 96\n\t}, \n\t{\n\t\t\"id\": \"3efb6a01-4e4a-4ce3-805a-332929b7746a\", \n\t\t\"countryId\": \"c7c44b2a-5a8d-46e6-8b7e-ccb30be4a64d\", \n\t\t\"administrativeAreaLevel1Id\": \"7bfe3853-b507-4ea9-a621-32a83082de7b\", \n\t\t\"code\": \"5v196z5b\", \n\t\t\"customCode\": \"n889qtperm\", \n\t\t\"name\": \"Incredible Fresh Pants\", \n\t\t\"slug\": \"impedit-sunt-fugit\", \n\t\t\"latitude\": 85303863199620770, \n\t\t\"longitude\": 84368181869765740, \n\t\t\"zoom\": 96\n\t}, \n\t{\n\t\t\"id\": \"55468839-52b4-4b99-b042-3c2ffd37e7aa\", \n\t\t\"countryId\": \"603d92e7-3783-4af7-9ee3-26790debba8a\", \n\t\t\"administrativeAreaLevel1Id\": \"9aa4771d-624a-4a94-a60d-fcf5e1c6abbc\", \n\t\t\"code\": \"kz9ygf7d\", \n\t\t\"customCode\": \"359tmmqowq\", \n\t\t\"name\": \"Small Concrete Chicken\", \n\t\t\"slug\": \"quo-deserunt-ut\", \n\t\t\"latitude\": 90247844603443230, \n\t\t\"longitude\": 31949478135671764, \n\t\t\"zoom\": 58\n\t}, \n\t{\n\t\t\"id\": \"5877d715-4b4f-4e76-a069-98a240c331b0\", \n\t\t\"countryId\": \"5d8afd94-c22c-46a3-a937-7b7e19d80e31\", \n\t\t\"administrativeAreaLevel1Id\": \"43ee6adb-500d-4de6-af5e-9bbc6ccfc16d\", \n\t\t\"code\": \"reaaep89\", \n\t\t\"customCode\": \"eadddsf8pt\", \n\t\t\"name\": \"Fantastic Granite Chips\", \n\t\t\"slug\": \"minus-totam-numquam\", \n\t\t\"latitude\": 59718512416601624, \n\t\t\"longitude\": 40066525719583870, \n\t\t\"zoom\": 49\n\t}\n]",
					"options": {
						"raw": {
							"language": "json"
						}
					}
				},
				"url": {
					"raw": "{{URL}}/common/administrative-areas-level-2",
					"host": [
						"{{URL}}"
					],
					"path": [
						"common",
						"administrative-areas-level-2"
					]
				}
			},
			"response": []
        },
        {
			"name": "REST - common/administrative-areas-level-2/paginate",
			"protocolProfileBehavior": {
				"disableBodyPruning": true
			},
			"request": {
				"method": "POST",
				"header": [
					{
						"key": "Content-Type",
						"name": "Content-Type",
						"type": "text",
						"value": "application/json"
					}				],
				"body": {
					"mode": "raw",
					"raw": "{\n\t\"query\":\n\t{\n\t\t\"offset\": 0,\n\t\t\"limit\": 10\n\t}\n}",
					"options": {
						"raw": {
							"language": "json"
						}
					}
				},
				"url": {
					"raw": "{{URL}}/common/administrative-areas-level-2/paginate",
					"host": [
						"{{URL}}"
					],
					"path": [
						"common",
                        "administrative-areas-level-2",
                        "paginate"
					]
				}
			},
			"response": []
        },
        {
			"name": "REST - common/administrative-areas-level-2",
			"protocolProfileBehavior": {
				"disableBodyPruning": true
			},
			"request": {
				"method": "GET",
				"header": [
					{
						"key": "Content-Type",
						"name": "Content-Type",
						"type": "text",
						"value": "application/json"
					}				],
				"body": {
					"mode": "raw",
					"raw": "{\n\t\"query\":\n\t{\n\t\t\"where\":\n\t\t{ \n\t\t\t\"id\": \"5b19d6ac-4081-573b-96b3-56964d5326a8\"\n\t\t}\n\t}\n}",
					"options": {
						"raw": {
							"language": "json"
						}
					}
				},
				"url": {
					"raw": "{{URL}}/common/administrative-areas-level-2",
					"host": [
						"{{URL}}"
					],
					"path": [
						"common",
						"administrative-areas-level-2"
					]
				}
			},
			"response": []
        },
        {
			"name": "REST - common/administrative-area-level-2",
			"protocolProfileBehavior": {
				"disableBodyPruning": true
			},
			"request": {
				"method": "GET",
				"header": [
					{
						"key": "Content-Type",
						"name": "Content-Type",
						"type": "text",
						"value": "application/json"
					}				],
				"body": {
					"mode": "raw",
					"raw": "{\n\t\"query\":\n\t{\n\t\t\"where\":\n\t\t{\n\t\t\t\"id\": \"5b19d6ac-4081-573b-96b3-56964d5326a8\"\n\t\t}\n\t}\n}",
					"options": {
						"raw": {
							"language": "json"
						}
					}
				},
				"url": {
					"raw": "{{URL}}/common/administrative-area-level-2",
					"host": [
						"{{URL}}"
					],
					"path": [
						"common",
						"administrative-area-level-2"
					]
				}
			},
			"response": []
        },
        {
			"name": "REST - common/administrative-area-level-2/{id}",
			"protocolProfileBehavior": {
				"disableBodyPruning": true
			},
			"request": {
				"method": "GET",
				"header": [
					{
						"key": "Content-Type",
						"name": "Content-Type",
						"type": "text",
						"value": "application/json"
					}				],
				"body": {
					"mode": "raw",
					"raw": "",
					"options": {
						"raw": {
							"language": "json"
						}
					}
				},
				"url": {
					"raw": "{{URL}}/common/administrative-area-level-2/5b19d6ac-4081-573b-96b3-56964d5326a8",
					"host": [
						"{{URL}}"
					],
					"path": [
						"common",
						"administrative-area-level-2",
						"5b19d6ac-4081-573b-96b3-56964d5326a8"
					]
				}
			},
			"response": []
        },
        {
			"name": "REST - common/administrative-area-level-2",
			"request": {
				"method": "PUT",
				"header": [
					{
						"key": "Content-Type",
						"name": "Content-Type",
						"type": "text",
						"value": "application/json"
					}				],
				"body": {
					"mode": "raw",
					"raw"   : "{\n\t\"id\": \"5b19d6ac-4081-573b-96b3-56964d5326a8\", \n\t\"countryId\": \"5b19d6ac-4081-573b-96b3-56964d5326a8\", \n\t\"administrativeAreaLevel1Id\": \"5b19d6ac-4081-573b-96b3-56964d5326a8\", \n\t\"code\": \"5c457i4g\", \n\t\"customCode\": \"x45vnecohq\", \n\t\"name\": \"Small Soft Keyboard\", \n\t\"slug\": \"quibusdam-dolorem-sit\", \n\t\"latitude\": 31678042730539796, \n\t\"longitude\": 33731241964782600, \n\t\"zoom\": 69\n}",
					"options": {
						"raw": {
							"language": "json"
						}
					}
				},
				"url": {
					"raw": "{{URL}}/common/administrative-area-level-2",
					"host": [
						"{{URL}}"
					],
					"path": [
						"common",
						"administrative-area-level-2"
					]
				}
			},
			"response": []
        },
        {
			"name": "REST - common/administrative-area-level-2/{id}",
			"request": {
				"method": "DELETE",
				"header": [
					{
						"key": "Content-Type",
						"name": "Content-Type",
						"type": "text",
						"value": "application/json"
					}				],
				"body": {
					"mode": "raw",
					"raw": "",
					"options": {
						"raw": {
							"language": "json"
						}
					}
				},
				"url": {
					"raw": "{{URL}}/common/administrative-area-level-2/5b19d6ac-4081-573b-96b3-56964d5326a8",
					"host": [
						"{{URL}}"
					],
					"path": [
						"common",
						"administrative-area-level-2",
						"5b19d6ac-4081-573b-96b3-56964d5326a8"
					]
				}
			},
			"response": []
		},
        {
			"name": "REST - common/administrative-areas-level-2",
			"request": {
				"method": "DELETE",
				"header": [
					{
						"key": "Content-Type",
						"name": "Content-Type",
						"type": "text",
						"value": "application/json"
					}				],
				"body": {
					"mode": "raw",
					"raw": "{\n\t\"query\":\n\t{\n\t\t\"where\":\n\t\t{\n\t\t\t\"id\":\n\t\t\t{\n\t\t\t\t\"[substring]\": \"\"\n\t\t\t}\n\t\t}\n\t}\n}",
					"options": {
						"raw": {
							"language": "json"
						}
					}
				},
				"url": {
					"raw": "{{URL}}/common/administrative-areas-level-2",
					"host": [
						"{{URL}}"
					],
					"path": [
						"common",
						"administrative-areas-level-2"
					]
				}
			},
			"response": []
		}
    ],
    "variable": [
		{
			"id": "827ab763-dc5c-46c1-ba1e-c47febc683be",
			"key": "URL",
			"value": "http://localhost:8080",
			"type": "string"
		}
	]
}